pickaxe/__init__.py
pickaxe/_pickaxe.abi3.so
pickaxe/_pickaxe.pyi
pickaxe/py.typed
python_pickaxe-0.5.5.dist-info/METADATA
python_pickaxe-0.5.5.dist-info/WHEEL
python_pickaxe-0.5.5.dist-info/RECORD
