Metadata-Version: 2.4
Name: python-pickaxe
Version: 0.5.5
Classifier: Programming Language :: Rust
Classifier: Programming Language :: Python :: Implementation :: CPython
Classifier: Programming Language :: Python :: Implementation :: PyPy
Summary: HTML data extraction library
Author: Tim Pogue <tim@emergentmethods.ai>
Author-email: Tim Pogue <tim@emergentmethods.ai>
License: MIT
Requires-Python: >=3.10, <4.0
Project-URL: repository, https://gitlab.com/emergentmethods/pickaxe
